program_counter/PC_Reg.sv
module PC_Reg #(
    parameter DATA_LENGTH = 32
) (
    input logic clk,
    input logic rst,
    input logic [DATA_LENGTH-1:0] next_PC,
    output logic [DATA_LENGTH-1:0] PC
);

always_ff @(posedge clk)begin
    if (rst) PC <= 0;
    else PC <= next_PC;
end
    
endmodule

program_counter/mux_2.sv
module mux_2 #(
    WIDTH = 32
) (
    input logic [WIDTH-1:0] d_0,
    input logic [WIDTH-1:0] d_1,
    input logic s,
    output logic [WIDTH-1:0] dout
);

assign dout = s ? d_1 : d_0;
    
endmodule

program_counter/adder.sv
module adder #(
    DATA_LENGTH = 32
) (
   input logic [DATA_LENGTH-1:0] in,
   input logic [DATA_LENGTH-1:0] N,
   output logic [DATA_LENGTH-1:0] out 
);

assign out = in + N;

endmodule

program_counter/top_PC.sv
module  top_PC #(
    parameter ADDRESS_WIDTH = 32
) (
    input logic clk,
    input logic rst,
    input logic [ADDRESS_WIDTH-1:0] ImmOp,
    input logic PCsrc,
    output logic [ADDRESS_WIDTH-1:0] PC
);

logic [ADDRESS_WIDTH-1:0] inc_PC;
logic [ADDRESS_WIDTH-1:0] next_PC;
logic [ADDRESS_WIDTH-1:0] branch_PC;

adder add_op(
    .in(PC),
    .N(ImmOp << 1), // 1 step in ImmOp corresponds to 2 bytes
    .out(branch_PC)
);

adder add_inc(
    .in(PC),
    .N(32'd4),
    .out(inc_PC)
);

mux_2 mux(
    .d_0(inc_PC),
    .d_1(branch_PC),
    .s(PCsrc),
    .dout(next_PC)
);

PC_Reg PC_Reg(
    .clk(clk),
    .rst(rst),
    .next_PC(next_PC),
    .PC(PC)
);

endmodule

program_counter/top.vcd
$version Generated by VerilatedVcd $end
$date Sun Nov 20 11:00:56 2022 $end
$timescale 1ps $end

 $scope module TOP $end
  $var wire 32 % ImmOp [31:0] $end
  $var wire 32 ' PC [31:0] $end
  $var wire  1 & PCsrc $end
  $var wire  1 # clk $end
  $var wire  1 $ rst $end
  $scope module top_PC $end
   $var wire 32 + ADDRESS_WIDTH [31:0] $end
   $var wire 32 % ImmOp [31:0] $end
   $var wire 32 ' PC [31:0] $end
   $var wire  1 & PCsrc $end
   $var wire 32 * branch_PC [31:0] $end
   $var wire  1 # clk $end
   $var wire 32 ( inc_PC [31:0] $end
   $var wire 32 ) next_PC [31:0] $end
   $var wire  1 $ rst $end
   $scope module PC_Reg $end
    $var wire 32 + DATA_LENGTH [31:0] $end
    $var wire 32 ' PC [31:0] $end
    $var wire  1 # clk $end
    $var wire 32 ) next_PC [31:0] $end
    $var wire  1 $ rst $end
   $upscope $end
   $scope module add_inc $end
    $var wire 32 + DATA_LENGTH [31:0] $end
    $var wire 32 , N [31:0] $end
    $var wire 32 ' in [31:0] $end
    $var wire 32 ( out [31:0] $end
   $upscope $end
   $scope module add_op $end
    $var wire 32 + DATA_LENGTH [31:0] $end
    $var wire 32 % N [31:0] $end
    $var wire 32 ' in [31:0] $end
    $var wire 32 * out [31:0] $end
   $upscope $end
   $scope module mux $end
    $var wire 32 + WIDTH [31:0] $end
    $var wire 32 ( d_0 [31:0] $end
    $var wire 32 * d_1 [31:0] $end
    $var wire 32 ) dout [31:0] $end
    $var wire  1 & s $end
   $upscope $end
  $upscope $end
 $upscope $end
$enddefinitions $end


#0
1#
0$
b00000000000000000000000000000000 %
0&
b00000000000000000000000000000000 '
b00000000000000000000000000000100 (
b00000000000000000000000000000100 )
b00000000000000000000000000000000 *
b00000000000000000000000000100000 +
b00000000000000000000000000000100 ,
#1
0#
#2
1#
b00000000000000000000000000000100 '
b00000000000000000000000000001000 (
b00000000000000000000000000001000 )
b00000000000000000000000000000100 *
#3
0#
#4
1#
b00000000000000000000000000001000 '
b00000000000000000000000000001100 (
b00000000000000000000000000001100 )
b00000000000000000000000000001000 *
#5
0#
#6
1#
b00000000000000000000000000001100 '
b00000000000000000000000000010000 (
b00000000000000000000000000010000 )
b00000000000000000000000000001100 *
#7
0#
#8
1#
b00000000000000000000000000010000 '
b00000000000000000000000000010100 (
b00000000000000000000000000010100 )
b00000000000000000000000000010000 *
#9
0#
#10
1#
b00000000000000000000000000010100 '
b00000000000000000000000000011000 (
b00000000000000000000000000011000 )
b00000000000000000000000000010100 *
#11
0#
#12
1#
b00000000000000000000000000011000 '
b00000000000000000000000000011100 (
b00000000000000000000000000011100 )
b00000000000000000000000000011000 *
#13
0#
#14
1#
b00000000000000000000000000011100 '
b00000000000000000000000000100000 (
b00000000000000000000000000100000 )
b00000000000000000000000000011100 *
#15
0#
#16
1#
b00000000000000000000000000100000 '
b00000000000000000000000000100100 (
b00000000000000000000000000100100 )
b00000000000000000000000000100000 *
#17
0#
#18
1#
b00000000000000000000000000100100 '
b00000000000000000000000000101000 (
b00000000000000000000000000101000 )
b00000000000000000000000000100100 *
#19
0#
#20
1#
b00000000000000000000000000101000 '
b00000000000000000000000000101100 (
b00000000000000000000000000101100 )
b00000000000000000000000000101000 *
#21
0#
#22
1#
b00000000000000000000000000101100 '
b00000000000000000000000000110000 (
b00000000000000000000000000110000 )
b00000000000000000000000000101100 *
#23
0#
#24
1#
b00000000000000000000000000110000 '
b00000000000000000000000000110100 (
b00000000000000000000000000110100 )
b00000000000000000000000000110000 *
#25
0#
#26
1#
b00000000000000000000000000110100 '
b00000000000000000000000000111000 (
b00000000000000000000000000111000 )
b00000000000000000000000000110100 *
#27
0#
#28
1#
b00000000000000000000000000111000 '
b00000000000000000000000000111100 (
b00000000000000000000000000111100 )
b00000000000000000000000000111000 *
#29
0#
#30
1#
b00000000000000000000000000111100 '
b00000000000000000000000001000000 (
b00000000000000000000000001000000 )
b00000000000000000000000000111100 *
#31
0#
#32
1#
b00000000000000000000000001000000 '
b00000000000000000000000001000100 (
b00000000000000000000000001000100 )
b00000000000000000000000001000000 *
#33
0#
#34
1#
b00000000000000000000000001000100 '
b00000000000000000000000001001000 (
b00000000000000000000000001001000 )
b00000000000000000000000001000100 *
#35
0#
#36
1#
b00000000000000000000000001001000 '
b00000000000000000000000001001100 (
b00000000000000000000000001001100 )
b00000000000000000000000001001000 *
#37
0#
#38
1#
b00000000000000000000000001001100 '
b00000000000000000000000001010000 (
b00000000000000000000000001010000 )
b00000000000000000000000001001100 *
#39
0#
#40
1#
b00000000000000000000000001010000 '
b00000000000000000000000001010100 (
b00000000000000000000000001010100 )
b00000000000000000000000001010000 *
#41
0#
#42
1#
b00000000000000000000000001010100 '
b00000000000000000000000001011000 (
b00000000000000000000000001011000 )
b00000000000000000000000001010100 *
#43
0#
#44
1#
1$
b00000000000000000000000001011000 '
b00000000000000000000000001011100 (
b00000000000000000000000001011100 )
b00000000000000000000000001011000 *
#45
0#
#46
1#
b00000000000000000000000000000000 '
b00000000000000000000000000000100 (
b00000000000000000000000000000100 )
b00000000000000000000000000000000 *
#47
0#
#48
1#
#49
0#
#50
1#
#51
0#
#52
1#
#53
0#
#54
1#
#55
0#
#56
1#
#57
0#
#58
1#
#59
0#
#60
1#
#61
0#
#62
1#
#63
0#
#64
1#
#65
0#
#66
1#
#67
0#
#68
1#
#69
0#
#70
1#
#71
0#
#72
1#
#73
0#
#74
1#
#75
0#
#76
1#
#77
0#
#78
1#
#79
0#
#80
1#
#81
0#
#82
1#
#83
0#
#84
1#
#85
0#
#86
1#
0$
1&
b00000000000000000000000000000000 )
