program_counter/PC_Reg.sv
module PC_Reg #(
    parameter DATA_LENGTH = 32
) (
    input logic clk,
    input logic rst,
    input logic [DATA_LENGTH-1:0] next_PC,
    output logic [DATA_LENGTH-1:0] PC
);

always_ff @(posedge clk)begin
    if (rst) PC <= 0;
    else PC <= next_PC;
end
    
endmodule

program_counter/mux_2.sv
module mux_2 #(
    WIDTH = 32
) (
    input logic [WIDTH-1:0] d_0,
    input logic [WIDTH-1:0] d_1,
    input logic s,
    output logic [WIDTH-1:0] dout
);

assign dout = s ? d_1 : d_0;
    
endmodule

program_counter/testing/adder.sv
module adder #(
    parameter DATA_LENGTH = 32
) (
   input logic [DATA_LENGTH-1:0] in,
   input logic [DATA_LENGTH-1:0] N,
   output logic [DATA_LENGTH-1:0] out 
);

assign out = in + N;

endmodule

program_counter/top_PC.sv
module  top_PC #(
    ADDRESS_WIDTH = 32
) (
    input wire clk,
    input wire rst,
    input wire[ADDRESS_WIDTH-1:0] ImmOP,
    input wire PCsrc,
    output wire [ADDRESS_WIDTH-1:0] PC
);

wire [ADDRESS_WIDTH-1:0] inc_PC;
wire [ADDRESS_WIDTH-1:0] next_PC;
wire [ADDRESS_WIDTH-1:0] branch_PC;

adder add_op(
    .in(PC),
    .N(ImmOP),
    .out(branch_PC)
);

adder add_inc(
    .in(PC),
    .N(32'd4),
    .out(inc_PC)
);

mux_2 mux(
    .d_0(inc_PC),
    .d_1(branch_PC),
    .s(PCsrc),
    .dout(next_PC)
);

PC_Reg PC_Reg(
    .clk(clk),
    .rst(rst),
    .next_PC(next_PC),
    .PC(PC)
);

endmodule

program_counter/testing/top_PC.vcd
$version Generated by VerilatedVcd $end
$date Sat Nov 19 12:01:16 2022 $end
$timescale 1ps $end

 $scope module TOP $end
  $var wire 32 % ImmOP [31:0] $end
  $var wire 32 ' PC [31:0] $end
  $var wire  1 & PCsrc $end
  $var wire  1 # clk $end
  $var wire  1 $ rst $end
  $scope module top_PC $end
   $var wire 32 + ADDRESS_WIDTH [31:0] $end
   $var wire 32 % ImmOP [31:0] $end
   $var wire 32 ' PC [31:0] $end
   $var wire  1 & PCsrc $end
   $var wire 32 * branch_PC [31:0] $end
   $var wire  1 # clk $end
   $var wire 32 ( inc_PC [31:0] $end
   $var wire 32 ) next_PC [31:0] $end
   $var wire  1 $ rst $end
   $scope module PC_Reg $end
    $var wire 32 + DATA_LENGTH [31:0] $end
    $var wire 32 ' PC [31:0] $end
    $var wire  1 # clk $end
    $var wire 32 ) next_PC [31:0] $end
    $var wire  1 $ rst $end
   $upscope $end
   $scope module add_inc $end
    $var wire 32 + DATA_LENGTH [31:0] $end
    $var wire 32 , N [31:0] $end
    $var wire 32 ' in [31:0] $end
    $var wire 32 ( out [31:0] $end
   $upscope $end
   $scope module add_op $end
    $var wire 32 + DATA_LENGTH [31:0] $end
    $var wire 32 % N [31:0] $end
    $var wire 32 ' in [31:0] $end
    $var wire 32 * out [31:0] $end
   $upscope $end
   $scope module mux $end
    $var wire 32 + WIDTH [31:0] $end
    $var wire 32 ( d_0 [31:0] $end
    $var wire 32 * d_1 [31:0] $end
    $var wire 32 ) dout [31:0] $end
    $var wire  1 & s $end
   $upscope $end
  $upscope $end
 $upscope $end
$enddefinitions $end


#0
0#
0$
b00000000000000000000000000100000 %
1&
b00000000000000000000000000000000 '
b00000000000000000000000000000100 (
b00000000000000000000000000100000 )
b00000000000000000000000000100000 *
b00000000000000000000000000100000 +
b00000000000000000000000000000100 ,
#1
1#
#2
0#
1$
#3
1#
#4
0#
#5
1#
#6
0#
0$
#7
1#
b00000000000000000000000000100000 '
b00000000000000000000000000100100 (
b00000000000000000000000001000000 )
b00000000000000000000000001000000 *
#8
0#
#9
1#
b00000000000000000000000001000000 '
b00000000000000000000000001000100 (
b00000000000000000000000001100000 )
b00000000000000000000000001100000 *
#10
0#
#11
1#
b00000000000000000000000001100000 '
b00000000000000000000000001100100 (
b00000000000000000000000010000000 )
b00000000000000000000000010000000 *
#12
0#
#13
1#
b00000000000000000000000010000000 '
b00000000000000000000000010000100 (
b00000000000000000000000010100000 )
b00000000000000000000000010100000 *
#14
0#
#15
1#
b00000000000000000000000010100000 '
b00000000000000000000000010100100 (
b00000000000000000000000011000000 )
b00000000000000000000000011000000 *
#16
0#
#17
1#
b00000000000000000000000011000000 '
b00000000000000000000000011000100 (
b00000000000000000000000011100000 )
b00000000000000000000000011100000 *
#18
0#
#19
1#
b00000000000000000000000011100000 '
b00000000000000000000000011100100 (
b00000000000000000000000100000000 )
b00000000000000000000000100000000 *
#20
0#
#21
1#
b00000000000000000000000100000000 '
b00000000000000000000000100000100 (
b00000000000000000000000100100000 )
b00000000000000000000000100100000 *
#22
0#
#23
1#
b00000000000000000000000100100000 '
b00000000000000000000000100100100 (
b00000000000000000000000101000000 )
b00000000000000000000000101000000 *
#24
0#
#25
1#
b00000000000000000000000101000000 '
b00000000000000000000000101000100 (
b00000000000000000000000101100000 )
b00000000000000000000000101100000 *
#26
0#
#27
1#
b00000000000000000000000101100000 '
b00000000000000000000000101100100 (
b00000000000000000000000110000000 )
b00000000000000000000000110000000 *
#28
0#
#29
1#
b00000000000000000000000110000000 '
b00000000000000000000000110000100 (
b00000000000000000000000110100000 )
b00000000000000000000000110100000 *
#30
0#
#31
1#
b00000000000000000000000110100000 '
b00000000000000000000000110100100 (
b00000000000000000000000111000000 )
b00000000000000000000000111000000 *
#32
0#
#33
1#
b00000000000000000000000111000000 '
b00000000000000000000000111000100 (
b00000000000000000000000111100000 )
b00000000000000000000000111100000 *
#34
0#
#35
1#
b00000000000000000000000111100000 '
b00000000000000000000000111100100 (
b00000000000000000000001000000000 )
b00000000000000000000001000000000 *
#36
0#
#37
1#
b00000000000000000000001000000000 '
b00000000000000000000001000000100 (
b00000000000000000000001000100000 )
b00000000000000000000001000100000 *
#38
0#
#39
1#
b00000000000000000000001000100000 '
b00000000000000000000001000100100 (
b00000000000000000000001001000000 )
b00000000000000000000001001000000 *
#40
0#
#41
1#
b00000000000000000000001001000000 '
b00000000000000000000001001000100 (
b00000000000000000000001001100000 )
b00000000000000000000001001100000 *
#42
0#
#43
1#
b00000000000000000000001001100000 '
b00000000000000000000001001100100 (
b00000000000000000000001010000000 )
b00000000000000000000001010000000 *
#44
0#
#45
1#
b00000000000000000000001010000000 '
b00000000000000000000001010000100 (
b00000000000000000000001010100000 )
b00000000000000000000001010100000 *
#46
0#
#47
1#
b00000000000000000000001010100000 '
b00000000000000000000001010100100 (
b00000000000000000000001011000000 )
b00000000000000000000001011000000 *
#48
0#
#49
1#
b00000000000000000000001011000000 '
b00000000000000000000001011000100 (
b00000000000000000000001011100000 )
b00000000000000000000001011100000 *
#50
0#
#51
1#
b00000000000000000000001011100000 '
b00000000000000000000001011100100 (
b00000000000000000000001100000000 )
b00000000000000000000001100000000 *
#52
0#
#53
1#
b00000000000000000000001100000000 '
b00000000000000000000001100000100 (
b00000000000000000000001100100000 )
b00000000000000000000001100100000 *
#54
0#
#55
1#
b00000000000000000000001100100000 '
b00000000000000000000001100100100 (
b00000000000000000000001101000000 )
b00000000000000000000001101000000 *
#56
0#
#57
1#
b00000000000000000000001101000000 '
b00000000000000000000001101000100 (
b00000000000000000000001101100000 )
b00000000000000000000001101100000 *
#58
0#
#59
1#
b00000000000000000000001101100000 '
b00000000000000000000001101100100 (
b00000000000000000000001110000000 )
b00000000000000000000001110000000 *
#60
0#
#61
1#
b00000000000000000000001110000000 '
b00000000000000000000001110000100 (
b00000000000000000000001110100000 )
b00000000000000000000001110100000 *
#62
0#
#63
1#
b00000000000000000000001110100000 '
b00000000000000000000001110100100 (
b00000000000000000000001111000000 )
b00000000000000000000001111000000 *
#64
0#
#65
1#
b00000000000000000000001111000000 '
b00000000000000000000001111000100 (
b00000000000000000000001111100000 )
b00000000000000000000001111100000 *
#66
0#
#67
1#
b00000000000000000000001111100000 '
b00000000000000000000001111100100 (
b00000000000000000000010000000000 )
b00000000000000000000010000000000 *
#68
0#
#69
1#
b00000000000000000000010000000000 '
b00000000000000000000010000000100 (
b00000000000000000000010000100000 )
b00000000000000000000010000100000 *
#70
0#
#71
1#
b00000000000000000000010000100000 '
b00000000000000000000010000100100 (
b00000000000000000000010001000000 )
b00000000000000000000010001000000 *
#72
0#
#73
1#
b00000000000000000000010001000000 '
b00000000000000000000010001000100 (
b00000000000000000000010001100000 )
b00000000000000000000010001100000 *
#74
0#
#75
1#
b00000000000000000000010001100000 '
b00000000000000000000010001100100 (
b00000000000000000000010010000000 )
b00000000000000000000010010000000 *
#76
0#
#77
1#
b00000000000000000000010010000000 '
b00000000000000000000010010000100 (
b00000000000000000000010010100000 )
b00000000000000000000010010100000 *
#78
0#
#79
1#
b00000000000000000000010010100000 '
b00000000000000000000010010100100 (
b00000000000000000000010011000000 )
b00000000000000000000010011000000 *
#80
0#
#81
1#
b00000000000000000000010011000000 '
b00000000000000000000010011000100 (
b00000000000000000000010011100000 )
b00000000000000000000010011100000 *
#82
0#
#83
1#
b00000000000000000000010011100000 '
b00000000000000000000010011100100 (
b00000000000000000000010100000000 )
b00000000000000000000010100000000 *
#84
0#
#85
1#
b00000000000000000000010100000000 '
b00000000000000000000010100000100 (
b00000000000000000000010100100000 )
b00000000000000000000010100100000 *
#86
0#
#87
1#
b00000000000000000000010100100000 '
b00000000000000000000010100100100 (
b00000000000000000000010101000000 )
b00000000000000000000010101000000 *
#88
0#
#89
1#
b00000000000000000000010101000000 '
b00000000000000000000010101000100 (
b00000000000000000000010101100000 )
b00000000000000000000010101100000 *
#90
0#
#91
1#
b00000000000000000000010101100000 '
b00000000000000000000010101100100 (
b00000000000000000000010110000000 )
b00000000000000000000010110000000 *
#92
0#
#93
1#
b00000000000000000000010110000000 '
b00000000000000000000010110000100 (
b00000000000000000000010110100000 )
b00000000000000000000010110100000 *
#94
0#
#95
1#
b00000000000000000000010110100000 '
b00000000000000000000010110100100 (
b00000000000000000000010111000000 )
b00000000000000000000010111000000 *
#96
0#
#97
1#
b00000000000000000000010111000000 '
b00000000000000000000010111000100 (
b00000000000000000000010111100000 )
b00000000000000000000010111100000 *
#98
0#
#99
1#
b00000000000000000000010111100000 '
b00000000000000000000010111100100 (
b00000000000000000000011000000000 )
b00000000000000000000011000000000 *
#100
0#
#101
1#
b00000000000000000000011000000000 '
b00000000000000000000011000000100 (
b00000000000000000000011000100000 )
b00000000000000000000011000100000 *
#102
0#
#103
1#
b00000000000000000000011000100000 '
b00000000000000000000011000100100 (
b00000000000000000000011001000000 )
b00000000000000000000011001000000 *
#104
0#
#105
1#
b00000000000000000000011001000000 '
b00000000000000000000011001000100 (
b00000000000000000000011001100000 )
b00000000000000000000011001100000 *
#106
0#
#107
1#
b00000000000000000000011001100000 '
b00000000000000000000011001100100 (
b00000000000000000000011010000000 )
b00000000000000000000011010000000 *
#108
0#
#109
1#
b00000000000000000000011010000000 '
b00000000000000000000011010000100 (
b00000000000000000000011010100000 )
b00000000000000000000011010100000 *
#110
0#
#111
1#
b00000000000000000000011010100000 '
b00000000000000000000011010100100 (
b00000000000000000000011011000000 )
b00000000000000000000011011000000 *
#112
0#
#113
1#
b00000000000000000000011011000000 '
b00000000000000000000011011000100 (
b00000000000000000000011011100000 )
b00000000000000000000011011100000 *
#114
0#
#115
1#
b00000000000000000000011011100000 '
b00000000000000000000011011100100 (
b00000000000000000000011100000000 )
b00000000000000000000011100000000 *
#116
0#
#117
1#
b00000000000000000000011100000000 '
b00000000000000000000011100000100 (
b00000000000000000000011100100000 )
b00000000000000000000011100100000 *
#118
0#
#119
1#
b00000000000000000000011100100000 '
b00000000000000000000011100100100 (
b00000000000000000000011101000000 )
b00000000000000000000011101000000 *
#120
0#
#121
1#
b00000000000000000000011101000000 '
b00000000000000000000011101000100 (
b00000000000000000000011101100000 )
b00000000000000000000011101100000 *
#122
0#
#123
1#
b00000000000000000000011101100000 '
b00000000000000000000011101100100 (
b00000000000000000000011110000000 )
b00000000000000000000011110000000 *
#124
0#
#125
1#
b00000000000000000000011110000000 '
b00000000000000000000011110000100 (
b00000000000000000000011110100000 )
b00000000000000000000011110100000 *
#126
0#
#127
1#
b00000000000000000000011110100000 '
b00000000000000000000011110100100 (
b00000000000000000000011111000000 )
b00000000000000000000011111000000 *
#128
0#
#129
1#
b00000000000000000000011111000000 '
b00000000000000000000011111000100 (
b00000000000000000000011111100000 )
b00000000000000000000011111100000 *
#130
0#
#131
1#
b00000000000000000000011111100000 '
b00000000000000000000011111100100 (
b00000000000000000000100000000000 )
b00000000000000000000100000000000 *
#132
0#
#133
1#
b00000000000000000000100000000000 '
b00000000000000000000100000000100 (
b00000000000000000000100000100000 )
b00000000000000000000100000100000 *
#134
0#
#135
1#
b00000000000000000000100000100000 '
b00000000000000000000100000100100 (
b00000000000000000000100001000000 )
b00000000000000000000100001000000 *
#136
0#
#137
1#
b00000000000000000000100001000000 '
b00000000000000000000100001000100 (
b00000000000000000000100001100000 )
b00000000000000000000100001100000 *
#138
0#
#139
1#
b00000000000000000000100001100000 '
b00000000000000000000100001100100 (
b00000000000000000000100010000000 )
b00000000000000000000100010000000 *
#140
0#
#141
1#
b00000000000000000000100010000000 '
b00000000000000000000100010000100 (
b00000000000000000000100010100000 )
b00000000000000000000100010100000 *
#142
0#
#143
1#
b00000000000000000000100010100000 '
b00000000000000000000100010100100 (
b00000000000000000000100011000000 )
b00000000000000000000100011000000 *
#144
0#
#145
1#
b00000000000000000000100011000000 '
b00000000000000000000100011000100 (
b00000000000000000000100011100000 )
b00000000000000000000100011100000 *
#146
0#
#147
1#
b00000000000000000000100011100000 '
b00000000000000000000100011100100 (
b00000000000000000000100100000000 )
b00000000000000000000100100000000 *
#148
0#
#149
1#
b00000000000000000000100100000000 '
b00000000000000000000100100000100 (
b00000000000000000000100100100000 )
b00000000000000000000100100100000 *
#150
0#
#151
1#
b00000000000000000000100100100000 '
b00000000000000000000100100100100 (
b00000000000000000000100101000000 )
b00000000000000000000100101000000 *
#152
0#
#153
1#
b00000000000000000000100101000000 '
b00000000000000000000100101000100 (
b00000000000000000000100101100000 )
b00000000000000000000100101100000 *
#154
0#
#155
1#
b00000000000000000000100101100000 '
b00000000000000000000100101100100 (
b00000000000000000000100110000000 )
b00000000000000000000100110000000 *
#156
0#
#157
1#
b00000000000000000000100110000000 '
b00000000000000000000100110000100 (
b00000000000000000000100110100000 )
b00000000000000000000100110100000 *
#158
0#
#159
1#
b00000000000000000000100110100000 '
b00000000000000000000100110100100 (
b00000000000000000000100111000000 )
b00000000000000000000100111000000 *
#160
0#
#161
1#
b00000000000000000000100111000000 '
b00000000000000000000100111000100 (
b00000000000000000000100111100000 )
b00000000000000000000100111100000 *
#162
0#
#163
1#
b00000000000000000000100111100000 '
b00000000000000000000100111100100 (
b00000000000000000000101000000000 )
b00000000000000000000101000000000 *
#164
0#
#165
1#
b00000000000000000000101000000000 '
b00000000000000000000101000000100 (
b00000000000000000000101000100000 )
b00000000000000000000101000100000 *
#166
0#
#167
1#
b00000000000000000000101000100000 '
b00000000000000000000101000100100 (
b00000000000000000000101001000000 )
b00000000000000000000101001000000 *
#168
0#
#169
1#
b00000000000000000000101001000000 '
b00000000000000000000101001000100 (
b00000000000000000000101001100000 )
b00000000000000000000101001100000 *
#170
0#
#171
1#
b00000000000000000000101001100000 '
b00000000000000000000101001100100 (
b00000000000000000000101010000000 )
b00000000000000000000101010000000 *
#172
0#
#173
1#
b00000000000000000000101010000000 '
b00000000000000000000101010000100 (
b00000000000000000000101010100000 )
b00000000000000000000101010100000 *
#174
0#
#175
1#
b00000000000000000000101010100000 '
b00000000000000000000101010100100 (
b00000000000000000000101011000000 )
b00000000000000000000101011000000 *
#176
0#
#177
1#
b00000000000000000000101011000000 '
b00000000000000000000101011000100 (
b00000000000000000000101011100000 )
b00000000000000000000101011100000 *
#178
0#
#179
1#
b00000000000000000000101011100000 '
b00000000000000000000101011100100 (
b00000000000000000000101100000000 )
b00000000000000000000101100000000 *
#180
0#
#181
1#
b00000000000000000000101100000000 '
b00000000000000000000101100000100 (
b00000000000000000000101100100000 )
b00000000000000000000101100100000 *
#182
0#
#183
1#
b00000000000000000000101100100000 '
b00000000000000000000101100100100 (
b00000000000000000000101101000000 )
b00000000000000000000101101000000 *
#184
0#
#185
1#
b00000000000000000000101101000000 '
b00000000000000000000101101000100 (
b00000000000000000000101101100000 )
b00000000000000000000101101100000 *
#186
0#
#187
1#
b00000000000000000000101101100000 '
b00000000000000000000101101100100 (
b00000000000000000000101110000000 )
b00000000000000000000101110000000 *
#188
0#
#189
1#
b00000000000000000000101110000000 '
b00000000000000000000101110000100 (
b00000000000000000000101110100000 )
b00000000000000000000101110100000 *
#190
0#
#191
1#
b00000000000000000000101110100000 '
b00000000000000000000101110100100 (
b00000000000000000000101111000000 )
b00000000000000000000101111000000 *
#192
0#
#193
1#
b00000000000000000000101111000000 '
b00000000000000000000101111000100 (
b00000000000000000000101111100000 )
b00000000000000000000101111100000 *
#194
0#
#195
1#
b00000000000000000000101111100000 '
b00000000000000000000101111100100 (
b00000000000000000000110000000000 )
b00000000000000000000110000000000 *
#196
0#
#197
1#
b00000000000000000000110000000000 '
b00000000000000000000110000000100 (
b00000000000000000000110000100000 )
b00000000000000000000110000100000 *
#198
0#
#199
1#
b00000000000000000000110000100000 '
b00000000000000000000110000100100 (
b00000000000000000000110001000000 )
b00000000000000000000110001000000 *
#200
0#
#201
1#
b00000000000000000000110001000000 '
b00000000000000000000110001000100 (
b00000000000000000000110001100000 )
b00000000000000000000110001100000 *
#202
0#
#203
1#
b00000000000000000000110001100000 '
b00000000000000000000110001100100 (
b00000000000000000000110010000000 )
b00000000000000000000110010000000 *
#204
0#
#205
1#
b00000000000000000000110010000000 '
b00000000000000000000110010000100 (
b00000000000000000000110010100000 )
b00000000000000000000110010100000 *
#206
0#
#207
1#
b00000000000000000000110010100000 '
b00000000000000000000110010100100 (
b00000000000000000000110011000000 )
b00000000000000000000110011000000 *
#208
0#
#209
1#
b00000000000000000000110011000000 '
b00000000000000000000110011000100 (
b00000000000000000000110011100000 )
b00000000000000000000110011100000 *
#210
0#
#211
1#
b00000000000000000000110011100000 '
b00000000000000000000110011100100 (
b00000000000000000000110100000000 )
b00000000000000000000110100000000 *
#212
0#
#213
1#
b00000000000000000000110100000000 '
b00000000000000000000110100000100 (
b00000000000000000000110100100000 )
b00000000000000000000110100100000 *
#214
0#
#215
1#
b00000000000000000000110100100000 '
b00000000000000000000110100100100 (
b00000000000000000000110101000000 )
b00000000000000000000110101000000 *
#216
0#
#217
1#
b00000000000000000000110101000000 '
b00000000000000000000110101000100 (
b00000000000000000000110101100000 )
b00000000000000000000110101100000 *
#218
0#
#219
1#
b00000000000000000000110101100000 '
b00000000000000000000110101100100 (
b00000000000000000000110110000000 )
b00000000000000000000110110000000 *
#220
0#
#221
1#
b00000000000000000000110110000000 '
b00000000000000000000110110000100 (
b00000000000000000000110110100000 )
b00000000000000000000110110100000 *
#222
0#
#223
1#
b00000000000000000000110110100000 '
b00000000000000000000110110100100 (
b00000000000000000000110111000000 )
b00000000000000000000110111000000 *
#224
0#
#225
1#
b00000000000000000000110111000000 '
b00000000000000000000110111000100 (
b00000000000000000000110111100000 )
b00000000000000000000110111100000 *
#226
0#
#227
1#
b00000000000000000000110111100000 '
b00000000000000000000110111100100 (
b00000000000000000000111000000000 )
b00000000000000000000111000000000 *
#228
0#
#229
1#
b00000000000000000000111000000000 '
b00000000000000000000111000000100 (
b00000000000000000000111000100000 )
b00000000000000000000111000100000 *
#230
0#
#231
1#
b00000000000000000000111000100000 '
b00000000000000000000111000100100 (
b00000000000000000000111001000000 )
b00000000000000000000111001000000 *
#232
0#
#233
1#
b00000000000000000000111001000000 '
b00000000000000000000111001000100 (
b00000000000000000000111001100000 )
b00000000000000000000111001100000 *
#234
0#
#235
1#
b00000000000000000000111001100000 '
b00000000000000000000111001100100 (
b00000000000000000000111010000000 )
b00000000000000000000111010000000 *
#236
0#
#237
1#
b00000000000000000000111010000000 '
b00000000000000000000111010000100 (
b00000000000000000000111010100000 )
b00000000000000000000111010100000 *
#238
0#
#239
1#
b00000000000000000000111010100000 '
b00000000000000000000111010100100 (
b00000000000000000000111011000000 )
b00000000000000000000111011000000 *
#240
0#
#241
1#
b00000000000000000000111011000000 '
b00000000000000000000111011000100 (
b00000000000000000000111011100000 )
b00000000000000000000111011100000 *
#242
0#
#243
1#
b00000000000000000000111011100000 '
b00000000000000000000111011100100 (
b00000000000000000000111100000000 )
b00000000000000000000111100000000 *
#244
0#
#245
1#
b00000000000000000000111100000000 '
b00000000000000000000111100000100 (
b00000000000000000000111100100000 )
b00000000000000000000111100100000 *
#246
0#
#247
1#
b00000000000000000000111100100000 '
b00000000000000000000111100100100 (
b00000000000000000000111101000000 )
b00000000000000000000111101000000 *
#248
0#
#249
1#
b00000000000000000000111101000000 '
b00000000000000000000111101000100 (
b00000000000000000000111101100000 )
b00000000000000000000111101100000 *
#250
0#
#251
1#
b00000000000000000000111101100000 '
b00000000000000000000111101100100 (
b00000000000000000000111110000000 )
b00000000000000000000111110000000 *
#252
0#
#253
1#
b00000000000000000000111110000000 '
b00000000000000000000111110000100 (
b00000000000000000000111110100000 )
b00000000000000000000111110100000 *
#254
0#
#255
1#
b00000000000000000000111110100000 '
b00000000000000000000111110100100 (
b00000000000000000000111111000000 )
b00000000000000000000111111000000 *
#256
0#
#257
1#
b00000000000000000000111111000000 '
b00000000000000000000111111000100 (
b00000000000000000000111111100000 )
b00000000000000000000111111100000 *
#258
0#
#259
1#
b00000000000000000000111111100000 '
b00000000000000000000111111100100 (
b00000000000000000001000000000000 )
b00000000000000000001000000000000 *
#260
0#
#261
1#
b00000000000000000001000000000000 '
b00000000000000000001000000000100 (
b00000000000000000001000000100000 )
b00000000000000000001000000100000 *
#262
0#
#263
1#
b00000000000000000001000000100000 '
b00000000000000000001000000100100 (
b00000000000000000001000001000000 )
b00000000000000000001000001000000 *
#264
0#
#265
1#
b00000000000000000001000001000000 '
b00000000000000000001000001000100 (
b00000000000000000001000001100000 )
b00000000000000000001000001100000 *
#266
0#
#267
1#
b00000000000000000001000001100000 '
b00000000000000000001000001100100 (
b00000000000000000001000010000000 )
b00000000000000000001000010000000 *
#268
0#
#269
1#
b00000000000000000001000010000000 '
b00000000000000000001000010000100 (
b00000000000000000001000010100000 )
b00000000000000000001000010100000 *
#270
0#
#271
1#
b00000000000000000001000010100000 '
b00000000000000000001000010100100 (
b00000000000000000001000011000000 )
b00000000000000000001000011000000 *
#272
0#
#273
1#
b00000000000000000001000011000000 '
b00000000000000000001000011000100 (
b00000000000000000001000011100000 )
b00000000000000000001000011100000 *
#274
0#
#275
1#
b00000000000000000001000011100000 '
b00000000000000000001000011100100 (
b00000000000000000001000100000000 )
b00000000000000000001000100000000 *
#276
0#
#277
1#
b00000000000000000001000100000000 '
b00000000000000000001000100000100 (
b00000000000000000001000100100000 )
b00000000000000000001000100100000 *
#278
0#
#279
1#
b00000000000000000001000100100000 '
b00000000000000000001000100100100 (
b00000000000000000001000101000000 )
b00000000000000000001000101000000 *
#280
0#
#281
1#
b00000000000000000001000101000000 '
b00000000000000000001000101000100 (
b00000000000000000001000101100000 )
b00000000000000000001000101100000 *
#282
0#
#283
1#
b00000000000000000001000101100000 '
b00000000000000000001000101100100 (
b00000000000000000001000110000000 )
b00000000000000000001000110000000 *
#284
0#
#285
1#
b00000000000000000001000110000000 '
b00000000000000000001000110000100 (
b00000000000000000001000110100000 )
b00000000000000000001000110100000 *
#286
0#
#287
1#
b00000000000000000001000110100000 '
b00000000000000000001000110100100 (
b00000000000000000001000111000000 )
b00000000000000000001000111000000 *
#288
0#
#289
1#
b00000000000000000001000111000000 '
b00000000000000000001000111000100 (
b00000000000000000001000111100000 )
b00000000000000000001000111100000 *
#290
0#
#291
1#
b00000000000000000001000111100000 '
b00000000000000000001000111100100 (
b00000000000000000001001000000000 )
b00000000000000000001001000000000 *
#292
0#
#293
1#
b00000000000000000001001000000000 '
b00000000000000000001001000000100 (
b00000000000000000001001000100000 )
b00000000000000000001001000100000 *
#294
0#
#295
1#
b00000000000000000001001000100000 '
b00000000000000000001001000100100 (
b00000000000000000001001001000000 )
b00000000000000000001001001000000 *
#296
0#
#297
1#
b00000000000000000001001001000000 '
b00000000000000000001001001000100 (
b00000000000000000001001001100000 )
b00000000000000000001001001100000 *
#298
0#
#299
1#
b00000000000000000001001001100000 '
b00000000000000000001001001100100 (
b00000000000000000001001010000000 )
b00000000000000000001001010000000 *
#300
0#
#301
1#
b00000000000000000001001010000000 '
b00000000000000000001001010000100 (
b00000000000000000001001010100000 )
b00000000000000000001001010100000 *
#302
0#
#303
1#
b00000000000000000001001010100000 '
b00000000000000000001001010100100 (
b00000000000000000001001011000000 )
b00000000000000000001001011000000 *
#304
0#
#305
1#
b00000000000000000001001011000000 '
b00000000000000000001001011000100 (
b00000000000000000001001011100000 )
b00000000000000000001001011100000 *
#306
0#
#307
1#
b00000000000000000001001011100000 '
b00000000000000000001001011100100 (
b00000000000000000001001100000000 )
b00000000000000000001001100000000 *
#308
0#
#309
1#
b00000000000000000001001100000000 '
b00000000000000000001001100000100 (
b00000000000000000001001100100000 )
b00000000000000000001001100100000 *
#310
0#
#311
1#
b00000000000000000001001100100000 '
b00000000000000000001001100100100 (
b00000000000000000001001101000000 )
b00000000000000000001001101000000 *
#312
0#
#313
1#
b00000000000000000001001101000000 '
b00000000000000000001001101000100 (
b00000000000000000001001101100000 )
b00000000000000000001001101100000 *
#314
0#
#315
1#
b00000000000000000001001101100000 '
b00000000000000000001001101100100 (
b00000000000000000001001110000000 )
b00000000000000000001001110000000 *
#316
0#
#317
1#
b00000000000000000001001110000000 '
b00000000000000000001001110000100 (
b00000000000000000001001110100000 )
b00000000000000000001001110100000 *
#318
0#
#319
1#
b00000000000000000001001110100000 '
b00000000000000000001001110100100 (
b00000000000000000001001111000000 )
b00000000000000000001001111000000 *
#320
0#
#321
1#
b00000000000000000001001111000000 '
b00000000000000000001001111000100 (
b00000000000000000001001111100000 )
b00000000000000000001001111100000 *
#322
0#
#323
1#
b00000000000000000001001111100000 '
b00000000000000000001001111100100 (
b00000000000000000001010000000000 )
b00000000000000000001010000000000 *
#324
0#
#325
1#
b00000000000000000001010000000000 '
b00000000000000000001010000000100 (
b00000000000000000001010000100000 )
b00000000000000000001010000100000 *
#326
0#
#327
1#
b00000000000000000001010000100000 '
b00000000000000000001010000100100 (
b00000000000000000001010001000000 )
b00000000000000000001010001000000 *
#328
0#
#329
1#
b00000000000000000001010001000000 '
b00000000000000000001010001000100 (
b00000000000000000001010001100000 )
b00000000000000000001010001100000 *
#330
0#
#331
1#
b00000000000000000001010001100000 '
b00000000000000000001010001100100 (
b00000000000000000001010010000000 )
b00000000000000000001010010000000 *
#332
0#
#333
1#
b00000000000000000001010010000000 '
b00000000000000000001010010000100 (
b00000000000000000001010010100000 )
b00000000000000000001010010100000 *
#334
0#
#335
1#
b00000000000000000001010010100000 '
b00000000000000000001010010100100 (
b00000000000000000001010011000000 )
b00000000000000000001010011000000 *
#336
0#
#337
1#
b00000000000000000001010011000000 '
b00000000000000000001010011000100 (
b00000000000000000001010011100000 )
b00000000000000000001010011100000 *
#338
0#
#339
1#
b00000000000000000001010011100000 '
b00000000000000000001010011100100 (
b00000000000000000001010100000000 )
b00000000000000000001010100000000 *
#340
0#
#341
1#
b00000000000000000001010100000000 '
b00000000000000000001010100000100 (
b00000000000000000001010100100000 )
b00000000000000000001010100100000 *
#342
0#
#343
1#
b00000000000000000001010100100000 '
b00000000000000000001010100100100 (
b00000000000000000001010101000000 )
b00000000000000000001010101000000 *
#344
0#
#345
1#
b00000000000000000001010101000000 '
b00000000000000000001010101000100 (
b00000000000000000001010101100000 )
b00000000000000000001010101100000 *
#346
0#
#347
1#
b00000000000000000001010101100000 '
b00000000000000000001010101100100 (
b00000000000000000001010110000000 )
b00000000000000000001010110000000 *
#348
0#
#349
1#
b00000000000000000001010110000000 '
b00000000000000000001010110000100 (
b00000000000000000001010110100000 )
b00000000000000000001010110100000 *
#350
0#
#351
1#
b00000000000000000001010110100000 '
b00000000000000000001010110100100 (
b00000000000000000001010111000000 )
b00000000000000000001010111000000 *
#352
0#
#353
1#
b00000000000000000001010111000000 '
b00000000000000000001010111000100 (
b00000000000000000001010111100000 )
b00000000000000000001010111100000 *
#354
0#
#355
1#
b00000000000000000001010111100000 '
b00000000000000000001010111100100 (
b00000000000000000001011000000000 )
b00000000000000000001011000000000 *
#356
0#
#357
1#
b00000000000000000001011000000000 '
b00000000000000000001011000000100 (
b00000000000000000001011000100000 )
b00000000000000000001011000100000 *
#358
0#
#359
1#
b00000000000000000001011000100000 '
b00000000000000000001011000100100 (
b00000000000000000001011001000000 )
b00000000000000000001011001000000 *
#360
0#
#361
1#
b00000000000000000001011001000000 '
b00000000000000000001011001000100 (
b00000000000000000001011001100000 )
b00000000000000000001011001100000 *
#362
0#
#363
1#
b00000000000000000001011001100000 '
b00000000000000000001011001100100 (
b00000000000000000001011010000000 )
b00000000000000000001011010000000 *
#364
0#
#365
1#
b00000000000000000001011010000000 '
b00000000000000000001011010000100 (
b00000000000000000001011010100000 )
b00000000000000000001011010100000 *
#366
0#
#367
1#
b00000000000000000001011010100000 '
b00000000000000000001011010100100 (
b00000000000000000001011011000000 )
b00000000000000000001011011000000 *
#368
0#
#369
1#
b00000000000000000001011011000000 '
b00000000000000000001011011000100 (
b00000000000000000001011011100000 )
b00000000000000000001011011100000 *
#370
0#
#371
1#
b00000000000000000001011011100000 '
b00000000000000000001011011100100 (
b00000000000000000001011100000000 )
b00000000000000000001011100000000 *
#372
0#
