control_unit,instr_mem,sign_extend/testing/sign_extend.sv
module sign_extend #(
    parameter data_width = 32,
              imm_width = 12
) (
    input logic [data_width-1:0] instruction,
    input logic ImmSrc,
    output logic [data_width-1:0] ImmOp
);

logic [imm_width-1:0] imm;

always_comb begin
    // Determine what bits of the instruction will be used in imm, based on ImmSrc.
    if (ImmSrc == 1) imm = instruction[31:20];
    else imm = {instruction[31], instruction[7], instruction[30:25], instruction[11:8]};

    // If the msb is a 0, we sign extend to 32-bits with 0s.
    if(imm[11] == 0) ImmOp = {{data_width - imm_width{1'b0}}, imm};
    // If the msb is a 1, we sign extend to 32-bits with 1s.
    else ImmOp = {{data_width - imm_width{1'b1}}, imm};
end
    
endmodule

control_unit,instr_mem,sign_extend/control_unit.sv
module control_unit #(
) (
    input logic EQ,
    input logic [14:12] funct3,
    input logic [6:0] opcode,
    output logic RegWrite,
    output logic ALUctrl,
    output logic ALUsrc,
    output logic ImmSrc,
    output logic PCsrc
);

// logic addi_instr;
// logic bne_instr;

typedef enum {UNDEFINED, ADDI, BNE} Instr;
Instr instr = UNDEFINED;

// Determine instruction
always_comb begin
    if (opcode == 7'b0010011 && funct3 == 3'b000)
        instr = ADDI;
    else if (opcode == 7'b1100011 && funct3 == 3'b001)
        instr = BNE;
    else
        instr = UNDEFINED;
end

// Set outputs
always_comb begin
    RegWrite = instr == ADDI;
    ALUctrl = 0; // Only one operation on ALUout for now, addition
    ALUsrc = instr == ADDI;
    ImmSrc = instr == ADDI;
    PCsrc = instr == BNE && EQ == 0;
end

endmodule

control_unit,instr_mem,sign_extend/testing/instr_mem.sv
module instr_mem #(
    parameter DATA_WIDTH = 8,
              ADDRESS_WIDTH = 32,
              INSTRUCTION_WIDTH = 32
) (
    input logic [ADDRESS_WIDTH-1:0] A,
    output logic [INSTRUCTION_WIDTH-1:0] RD
);

logic [DATA_WIDTH-1:0] rom_array [27:0];
logic [DATA_WIDTH-1:0] byte1;
logic [DATA_WIDTH-1:0] byte2;
logic [DATA_WIDTH-1:0] byte3;
logic [DATA_WIDTH-1:0] byte4;

initial begin
        $display("Loading instructions.");
        $readmemh("instructions.mem", rom_array);
end

always_comb begin
    // Output is asynchronous.
    byte1 = rom_array [A];
    byte2 = rom_array [A + 1];
    byte3 = rom_array [A + 2];
    byte4 = rom_array [A + 3];
    RD = {byte4, byte3, byte2, byte1};
end
    
endmodule

control_unit,instr_mem,sign_extend/top_control_mem_extend.sv
module top_control_mem_extend #(
    parameter WIDTH = 32
) (
    input wire [WIDTH-1:0] PC,
    input wire EQ,
    output wire [5:1] rs1,
    output wire [5:1] rs2,
    output wire [5:1] rd,
    output wire RegWrite,
    output wire ALUctrl,
    output wire ALUsrc,
    output wire ImmSrc,
    output wire PCsrc,
    output wire [WIDTH-1:0] ImmOp

);

// Interconnect wires.
wire [WIDTH-1:0] instr;

// Lower-level modules incorporated.

instr_mem InstructionMemory (
    .A (PC),
    .RD (instr)
);

control_unit ControlUnit (
    .EQ (EQ),
    .funct3(instr[14:12]),
    .opcode(instr[6:0]),
    .RegWrite (RegWrite),
    .ALUctrl (ALUctrl),
    .ALUsrc (ALUsrc),
    .ImmSrc (ImmSrc),
    .PCsrc (PCsrc)
);

sign_extend SignExtend (
    .instruction (instr),
    .ImmSrc (ImmSrc),
    .ImmOp (ImmOp)
);
    
endmodule

control_unit,instr_mem,sign_extend/testing/top.vcd
$version Generated by VerilatedVcd $end
$date Mon Nov 21 11:21:54 2022 $end
$timescale 1ps $end

 $scope module TOP $end
  $var wire  1 N ALUctrl $end
  $var wire  1 O ALUsrc $end
  $var wire  1 I EQ $end
  $var wire 32 R ImmOp [31:0] $end
  $var wire  1 P ImmSrc $end
  $var wire 32 H PC [31:0] $end
  $var wire  1 Q PCsrc $end
  $var wire  1 M RegWrite $end
  $var wire  5 L rd [5:1] $end
  $var wire  5 J rs1 [5:1] $end
  $var wire  5 K rs2 [5:1] $end
  $scope module top_control_mem_extend $end
   $var wire  1 N ALUctrl $end
   $var wire  1 O ALUsrc $end
   $var wire  1 I EQ $end
   $var wire 32 R ImmOp [31:0] $end
   $var wire  1 P ImmSrc $end
   $var wire 32 H PC [31:0] $end
   $var wire  1 Q PCsrc $end
   $var wire  1 M RegWrite $end
   $var wire 32 S WIDTH [31:0] $end
   $var wire 32 ? instr [31:0] $end
   $var wire  5 L rd [5:1] $end
   $var wire  5 J rs1 [5:1] $end
   $var wire  5 K rs2 [5:1] $end
   $scope module ControlUnit $end
    $var wire  1 N ALUctrl $end
    $var wire  1 O ALUsrc $end
    $var wire  1 I EQ $end
    $var wire  1 P ImmSrc $end
    $var wire  1 Q PCsrc $end
    $var wire  1 M RegWrite $end
    $var wire  3 @ funct3 [14:12] $end
    $var wire 32 B instr [31:0] $end
    $var wire  7 A opcode [6:0] $end
   $upscope $end
   $scope module InstructionMemory $end
    $var wire 32 H A [31:0] $end
    $var wire 32 S ADDRESS_WIDTH [31:0] $end
    $var wire 32 T DATA_WIDTH [31:0] $end
    $var wire 32 S INSTRUCTION_WIDTH [31:0] $end
    $var wire 32 ? RD [31:0] $end
    $var wire  8 C byte1 [7:0] $end
    $var wire  8 D byte2 [7:0] $end
    $var wire  8 E byte3 [7:0] $end
    $var wire  8 F byte4 [7:0] $end
    $var wire  8 # rom_array[0] [7:0] $end
    $var wire  8 - rom_array[10] [7:0] $end
    $var wire  8 . rom_array[11] [7:0] $end
    $var wire  8 / rom_array[12] [7:0] $end
    $var wire  8 0 rom_array[13] [7:0] $end
    $var wire  8 1 rom_array[14] [7:0] $end
    $var wire  8 2 rom_array[15] [7:0] $end
    $var wire  8 3 rom_array[16] [7:0] $end
    $var wire  8 4 rom_array[17] [7:0] $end
    $var wire  8 5 rom_array[18] [7:0] $end
    $var wire  8 6 rom_array[19] [7:0] $end
    $var wire  8 $ rom_array[1] [7:0] $end
    $var wire  8 7 rom_array[20] [7:0] $end
    $var wire  8 8 rom_array[21] [7:0] $end
    $var wire  8 9 rom_array[22] [7:0] $end
    $var wire  8 : rom_array[23] [7:0] $end
    $var wire  8 ; rom_array[24] [7:0] $end
    $var wire  8 < rom_array[25] [7:0] $end
    $var wire  8 = rom_array[26] [7:0] $end
    $var wire  8 > rom_array[27] [7:0] $end
    $var wire  8 % rom_array[2] [7:0] $end
    $var wire  8 & rom_array[3] [7:0] $end
    $var wire  8 ' rom_array[4] [7:0] $end
    $var wire  8 ( rom_array[5] [7:0] $end
    $var wire  8 ) rom_array[6] [7:0] $end
    $var wire  8 * rom_array[7] [7:0] $end
    $var wire  8 + rom_array[8] [7:0] $end
    $var wire  8 , rom_array[9] [7:0] $end
   $upscope $end
   $scope module SignExtend $end
    $var wire 32 R ImmOp [31:0] $end
    $var wire  1 P ImmSrc $end
    $var wire 32 S data_width [31:0] $end
    $var wire 12 G imm [11:0] $end
    $var wire 32 U imm_width [31:0] $end
    $var wire 32 ? instruction [31:0] $end
   $upscope $end
  $upscope $end
 $upscope $end
$enddefinitions $end


#0
b00001111 #
b11110000 $
b00000011 %
b00010011 &
b00000000 '
b00000000 (
b00000101 )
b00010011 *
b00000000 +
b00000000 ,
b00000101 -
b10010011 .
b00000000 /
b00000101 0
b10000101 1
b00010011 2
b00000000 3
b00010101 4
b10000101 5
b10010011 6
b11111110 7
b01100101 8
b10011000 9
b11100011 :
b11111110 ;
b00000011 <
b00010000 =
b11100011 >
b00001111111100000000001100010011 ?
b000 @
b0010011 A
b00000000000000000000000000000001 B
b00001111 C
b11110000 D
b00000011 E
b00010011 F
b000011111111 G
b00000000000000000000000000000000 H
0I
b00000 J
b00000 K
b00000 L
1M
0N
1O
1P
0Q
b00000000000000000000000011111111 R
b00000000000000000000000000100000 S
b00000000000000000000000000001000 T
b00000000000000000000000000001100 U
#1
b00000000000000000000010100010011 ?
b00000000 C
b00000000 D
b00000101 E
b000000000000 G
b00000000000000000000000000000100 H
b00000000000000000000000000000000 R
#2
b00000000000000000000010110010011 ?
b10010011 F
b00000000000000000000000000001000 H
#3
b00000000000001011000010100010011 ?
b00000101 D
b10000101 E
b00010011 F
b00000000000000000000000000001100 H
#4
b00000000000101011000010110010011 ?
b00010101 D
b10010011 F
b000000000001 G
b00000000000000000000000000010000 H
b00000000000000000000000000000001 R
#5
b11111110011001011001100011100011 ?
b001 @
b1100011 A
b00000000000000000000000000000010 B
b11111110 C
b01100101 D
b10011000 E
b11100011 F
b111111111000 G
b00000000000000000000000000010100 H
0M
0O
0P
1Q
b11111111111111111111111111111000 R
#6
b11111110000000110001000011100011 ?
b00000011 D
b00010000 E
b111111110000 G
b00000000000000000000000000011000 H
b11111111111111111111111111110000 R
#7
b00001111111100000000001100010011 ?
b000 @
b0010011 A
b00000000000000000000000000000001 B
b00001111 C
b11110000 D
b00000011 E
b00010011 F
b000011111111 G
b00000000000000000000000000000000 H
1I
1M
1O
1P
0Q
b00000000000000000000000011111111 R
#8
b00000000000000000000010100010011 ?
b00000000 C
b00000000 D
b00000101 E
b000000000000 G
b00000000000000000000000000000100 H
b00000000000000000000000000000000 R
#9
b00000000000000000000010110010011 ?
b10010011 F
b00000000000000000000000000001000 H
#10
b00000000000001011000010100010011 ?
b00000101 D
b10000101 E
b00010011 F
b00000000000000000000000000001100 H
#11
b00000000000101011000010110010011 ?
b00010101 D
b10010011 F
b000000000001 G
b00000000000000000000000000010000 H
b00000000000000000000000000000001 R
#12
b11111110011001011001100011100011 ?
b001 @
b1100011 A
b00000000000000000000000000000010 B
b11111110 C
b01100101 D
b10011000 E
b11100011 F
b111111111000 G
b00000000000000000000000000010100 H
0M
0O
0P
b11111111111111111111111111111000 R
#13
b11111110000000110001000011100011 ?
b00000011 D
b00010000 E
b111111110000 G
b00000000000000000000000000011000 H
b11111111111111111111111111110000 R
#14
b00001111111100000000001100010011 ?
b000 @
b0010011 A
b00000000000000000000000000000001 B
b00001111 C
b11110000 D
b00000011 E
b00010011 F
b000011111111 G
b00000000000000000000000000000000 H
0I
1M
1O
1P
b00000000000000000000000011111111 R
#15
b00000000000000000000010100010011 ?
b00000000 C
b00000000 D
b00000101 E
b000000000000 G
b00000000000000000000000000000100 H
b00000000000000000000000000000000 R
#16
b00000000000000000000010110010011 ?
b10010011 F
b00000000000000000000000000001000 H
#17
b00000000000001011000010100010011 ?
b00000101 D
b10000101 E
b00010011 F
b00000000000000000000000000001100 H
#18
b00000000000101011000010110010011 ?
b00010101 D
b10010011 F
b000000000001 G
b00000000000000000000000000010000 H
b00000000000000000000000000000001 R
#19
b11111110011001011001100011100011 ?
b001 @
b1100011 A
b00000000000000000000000000000010 B
b11111110 C
b01100101 D
b10011000 E
b11100011 F
b111111111000 G
b00000000000000000000000000010100 H
0M
0O
0P
1Q
b11111111111111111111111111111000 R
#20
b11111110000000110001000011100011 ?
b00000011 D
b00010000 E
b111111110000 G
b00000000000000000000000000011000 H
b11111111111111111111111111110000 R
#21
b00001111111100000000001100010011 ?
b000 @
b0010011 A
b00000000000000000000000000000001 B
b00001111 C
b11110000 D
b00000011 E
b00010011 F
b000011111111 G
b00000000000000000000000000000000 H
1I
1M
1O
1P
0Q
b00000000000000000000000011111111 R
#22
b00000000000000000000010100010011 ?
b00000000 C
b00000000 D
b00000101 E
b000000000000 G
b00000000000000000000000000000100 H
b00000000000000000000000000000000 R
#23
b00000000000000000000010110010011 ?
b10010011 F
b00000000000000000000000000001000 H
#24
b00000000000001011000010100010011 ?
b00000101 D
b10000101 E
b00010011 F
b00000000000000000000000000001100 H
#25
b00000000000101011000010110010011 ?
b00010101 D
b10010011 F
b000000000001 G
b00000000000000000000000000010000 H
b00000000000000000000000000000001 R
#26
b11111110011001011001100011100011 ?
b001 @
b1100011 A
b00000000000000000000000000000010 B
b11111110 C
b01100101 D
b10011000 E
b11100011 F
b111111111000 G
b00000000000000000000000000010100 H
0M
0O
0P
b11111111111111111111111111111000 R
#27
b11111110000000110001000011100011 ?
b00000011 D
b00010000 E
b111111110000 G
b00000000000000000000000000011000 H
b11111111111111111111111111110000 R
#28
b00001111111100000000001100010011 ?
b000 @
b0010011 A
b00000000000000000000000000000001 B
b00001111 C
b11110000 D
b00000011 E
b00010011 F
b000011111111 G
b00000000000000000000000000000000 H
0I
1M
1O
1P
b00000000000000000000000011111111 R
#29
b00000000000000000000010100010011 ?
b00000000 C
b00000000 D
b00000101 E
b000000000000 G
b00000000000000000000000000000100 H
b00000000000000000000000000000000 R
#30
b00000000000000000000010110010011 ?
b10010011 F
b00000000000000000000000000001000 H
#31
b00000000000001011000010100010011 ?
b00000101 D
b10000101 E
b00010011 F
b00000000000000000000000000001100 H
#32
b00000000000101011000010110010011 ?
b00010101 D
b10010011 F
b000000000001 G
b00000000000000000000000000010000 H
b00000000000000000000000000000001 R
#33
b11111110011001011001100011100011 ?
b001 @
b1100011 A
b00000000000000000000000000000010 B
b11111110 C
b01100101 D
b10011000 E
b11100011 F
b111111111000 G
b00000000000000000000000000010100 H
0M
0O
0P
1Q
b11111111111111111111111111111000 R
#34
b11111110000000110001000011100011 ?
b00000011 D
b00010000 E
b111111110000 G
b00000000000000000000000000011000 H
b11111111111111111111111111110000 R
#35
b00001111111100000000001100010011 ?
b000 @
b0010011 A
b00000000000000000000000000000001 B
b00001111 C
b11110000 D
b00000011 E
b00010011 F
b000011111111 G
b00000000000000000000000000000000 H
1I
1M
1O
1P
0Q
b00000000000000000000000011111111 R
#36
b00000000000000000000010100010011 ?
b00000000 C
b00000000 D
b00000101 E
b000000000000 G
b00000000000000000000000000000100 H
b00000000000000000000000000000000 R
#37
b00000000000000000000010110010011 ?
b10010011 F
b00000000000000000000000000001000 H
#38
b00000000000001011000010100010011 ?
b00000101 D
b10000101 E
b00010011 F
b00000000000000000000000000001100 H
#39
b00000000000101011000010110010011 ?
b00010101 D
b10010011 F
b000000000001 G
b00000000000000000000000000010000 H
b00000000000000000000000000000001 R
#40
b11111110011001011001100011100011 ?
b001 @
b1100011 A
b00000000000000000000000000000010 B
b11111110 C
b01100101 D
b10011000 E
b11100011 F
b111111111000 G
b00000000000000000000000000010100 H
0M
0O
0P
b11111111111111111111111111111000 R
#41
b11111110000000110001000011100011 ?
b00000011 D
b00010000 E
b111111110000 G
b00000000000000000000000000011000 H
b11111111111111111111111111110000 R
#42
b00001111111100000000001100010011 ?
b000 @
b0010011 A
b00000000000000000000000000000001 B
b00001111 C
b11110000 D
b00000011 E
b00010011 F
b000011111111 G
b00000000000000000000000000000000 H
0I
1M
1O
1P
b00000000000000000000000011111111 R
#43
b00000000000000000000010100010011 ?
b00000000 C
b00000000 D
b00000101 E
b000000000000 G
b00000000000000000000000000000100 H
b00000000000000000000000000000000 R
#44
b00000000000000000000010110010011 ?
b10010011 F
b00000000000000000000000000001000 H
#45
b00000000000001011000010100010011 ?
b00000101 D
b10000101 E
b00010011 F
b00000000000000000000000000001100 H
#46
b00000000000101011000010110010011 ?
b00010101 D
b10010011 F
b000000000001 G
b00000000000000000000000000010000 H
b00000000000000000000000000000001 R
#47
b11111110011001011001100011100011 ?
b001 @
b1100011 A
b00000000000000000000000000000010 B
b11111110 C
b01100101 D
b10011000 E
b11100011 F
b111111111000 G
b00000000000000000000000000010100 H
0M
0O
0P
1Q
b11111111111111111111111111111000 R
#48
b11111110000000110001000011100011 ?
b00000011 D
b00010000 E
b111111110000 G
b00000000000000000000000000011000 H
b11111111111111111111111111110000 R
#49
b00001111111100000000001100010011 ?
b000 @
b0010011 A
b00000000000000000000000000000001 B
b00001111 C
b11110000 D
b00000011 E
b00010011 F
b000011111111 G
b00000000000000000000000000000000 H
1I
1M
1O
1P
0Q
b00000000000000000000000011111111 R
#50
b00000000000000000000010100010011 ?
b00000000 C
b00000000 D
b00000101 E
b000000000000 G
b00000000000000000000000000000100 H
b00000000000000000000000000000000 R
#51
b00000000000000000000010110010011 ?
b10010011 F
b00000000000000000000000000001000 H
#52
b00000000000001011000010100010011 ?
b00000101 D
b10000101 E
b00010011 F
b00000000000000000000000000001100 H
#53
b00000000000101011000010110010011 ?
b00010101 D
b10010011 F
b000000000001 G
b00000000000000000000000000010000 H
b00000000000000000000000000000001 R
#54
b11111110011001011001100011100011 ?
b001 @
b1100011 A
b00000000000000000000000000000010 B
b11111110 C
b01100101 D
b10011000 E
b11100011 F
b111111111000 G
b00000000000000000000000000010100 H
0M
0O
0P
b11111111111111111111111111111000 R
#55
b11111110000000110001000011100011 ?
b00000011 D
b00010000 E
b111111110000 G
b00000000000000000000000000011000 H
b11111111111111111111111111110000 R
#56
b00001111111100000000001100010011 ?
b000 @
b0010011 A
b00000000000000000000000000000001 B
b00001111 C
b11110000 D
b00000011 E
b00010011 F
b000011111111 G
b00000000000000000000000000000000 H
0I
1M
1O
1P
b00000000000000000000000011111111 R
#57
b00000000000000000000010100010011 ?
b00000000 C
b00000000 D
b00000101 E
b000000000000 G
b00000000000000000000000000000100 H
b00000000000000000000000000000000 R
#58
b00000000000000000000010110010011 ?
b10010011 F
b00000000000000000000000000001000 H
#59
b00000000000001011000010100010011 ?
b00000101 D
b10000101 E
b00010011 F
b00000000000000000000000000001100 H
#60
b00000000000101011000010110010011 ?
b00010101 D
b10010011 F
b000000000001 G
b00000000000000000000000000010000 H
b00000000000000000000000000000001 R
#61
b11111110011001011001100011100011 ?
b001 @
b1100011 A
b00000000000000000000000000000010 B
b11111110 C
b01100101 D
b10011000 E
b11100011 F
b111111111000 G
b00000000000000000000000000010100 H
0M
0O
0P
1Q
b11111111111111111111111111111000 R
#62
b11111110000000110001000011100011 ?
b00000011 D
b00010000 E
b111111110000 G
b00000000000000000000000000011000 H
b11111111111111111111111111110000 R
#63
b00001111111100000000001100010011 ?
b000 @
b0010011 A
b00000000000000000000000000000001 B
b00001111 C
b11110000 D
b00000011 E
b00010011 F
b000011111111 G
b00000000000000000000000000000000 H
1I
1M
1O
1P
0Q
b00000000000000000000000011111111 R
#64
b00000000000000000000010100010011 ?
b00000000 C
b00000000 D
b00000101 E
b000000000000 G
b00000000000000000000000000000100 H
b00000000000000000000000000000000 R
#65
b00000000000000000000010110010011 ?
b10010011 F
b00000000000000000000000000001000 H
#66
b00000000000001011000010100010011 ?
b00000101 D
b10000101 E
b00010011 F
b00000000000000000000000000001100 H
#67
b00000000000101011000010110010011 ?
b00010101 D
b10010011 F
b000000000001 G
b00000000000000000000000000010000 H
b00000000000000000000000000000001 R
#68
b11111110011001011001100011100011 ?
b001 @
b1100011 A
b00000000000000000000000000000010 B
b11111110 C
b01100101 D
b10011000 E
b11100011 F
b111111111000 G
b00000000000000000000000000010100 H
0M
0O
0P
b11111111111111111111111111111000 R
#69
b11111110000000110001000011100011 ?
b00000011 D
b00010000 E
b111111110000 G
b00000000000000000000000000011000 H
b11111111111111111111111111110000 R
#70
b00001111111100000000001100010011 ?
b000 @
b0010011 A
b00000000000000000000000000000001 B
b00001111 C
b11110000 D
b00000011 E
b00010011 F
b000011111111 G
b00000000000000000000000000000000 H
0I
1M
1O
1P
b00000000000000000000000011111111 R
#71
b00000000000000000000010100010011 ?
b00000000 C
b00000000 D
b00000101 E
b000000000000 G
b00000000000000000000000000000100 H
b00000000000000000000000000000000 R
#72
b00000000000000000000010110010011 ?
b10010011 F
b00000000000000000000000000001000 H
#73
b00000000000001011000010100010011 ?
b00000101 D
b10000101 E
b00010011 F
b00000000000000000000000000001100 H
#74
b00000000000101011000010110010011 ?
b00010101 D
b10010011 F
b000000000001 G
b00000000000000000000000000010000 H
b00000000000000000000000000000001 R
#75
b11111110011001011001100011100011 ?
b001 @
b1100011 A
b00000000000000000000000000000010 B
b11111110 C
b01100101 D
b10011000 E
b11100011 F
b111111111000 G
b00000000000000000000000000010100 H
0M
0O
0P
1Q
b11111111111111111111111111111000 R
#76
b11111110000000110001000011100011 ?
b00000011 D
b00010000 E
b111111110000 G
b00000000000000000000000000011000 H
b11111111111111111111111111110000 R
#77
b00001111111100000000001100010011 ?
b000 @
b0010011 A
b00000000000000000000000000000001 B
b00001111 C
b11110000 D
b00000011 E
b00010011 F
b000011111111 G
b00000000000000000000000000000000 H
1I
1M
1O
1P
0Q
b00000000000000000000000011111111 R
#78
b00000000000000000000010100010011 ?
b00000000 C
b00000000 D
b00000101 E
b000000000000 G
b00000000000000000000000000000100 H
b00000000000000000000000000000000 R
#79
b00000000000000000000010110010011 ?
b10010011 F
b00000000000000000000000000001000 H
#80
b00000000000001011000010100010011 ?
b00000101 D
b10000101 E
b00010011 F
b00000000000000000000000000001100 H
#81
b00000000000101011000010110010011 ?
b00010101 D
b10010011 F
b000000000001 G
b00000000000000000000000000010000 H
b00000000000000000000000000000001 R
#82
b11111110011001011001100011100011 ?
b001 @
b1100011 A
b00000000000000000000000000000010 B
b11111110 C
b01100101 D
b10011000 E
b11100011 F
b111111111000 G
b00000000000000000000000000010100 H
0M
0O
0P
b11111111111111111111111111111000 R
#83
b11111110000000110001000011100011 ?
b00000011 D
b00010000 E
b111111110000 G
b00000000000000000000000000011000 H
b11111111111111111111111111110000 R
#84
b00001111111100000000001100010011 ?
b000 @
b0010011 A
b00000000000000000000000000000001 B
b00001111 C
b11110000 D
b00000011 E
b00010011 F
b000011111111 G
b00000000000000000000000000000000 H
0I
1M
1O
1P
b00000000000000000000000011111111 R
#85
b00000000000000000000010100010011 ?
b00000000 C
b00000000 D
b00000101 E
b000000000000 G
b00000000000000000000000000000100 H
b00000000000000000000000000000000 R
#86
b00000000000000000000010110010011 ?
b10010011 F
b00000000000000000000000000001000 H
#87
b00000000000001011000010100010011 ?
b00000101 D
b10000101 E
b00010011 F
b00000000000000000000000000001100 H
#88
b00000000000101011000010110010011 ?
b00010101 D
b10010011 F
b000000000001 G
b00000000000000000000000000010000 H
b00000000000000000000000000000001 R
#89
b11111110011001011001100011100011 ?
b001 @
b1100011 A
b00000000000000000000000000000010 B
b11111110 C
b01100101 D
b10011000 E
b11100011 F
b111111111000 G
b00000000000000000000000000010100 H
0M
0O
0P
1Q
b11111111111111111111111111111000 R
#90
b11111110000000110001000011100011 ?
b00000011 D
b00010000 E
b111111110000 G
b00000000000000000000000000011000 H
b11111111111111111111111111110000 R
#91
b00001111111100000000001100010011 ?
b000 @
b0010011 A
b00000000000000000000000000000001 B
b00001111 C
b11110000 D
b00000011 E
b00010011 F
b000011111111 G
b00000000000000000000000000000000 H
1I
1M
1O
1P
0Q
b00000000000000000000000011111111 R
#92
b00000000000000000000010100010011 ?
b00000000 C
b00000000 D
b00000101 E
b000000000000 G
b00000000000000000000000000000100 H
b00000000000000000000000000000000 R
#93
b00000000000000000000010110010011 ?
b10010011 F
b00000000000000000000000000001000 H
#94
b00000000000001011000010100010011 ?
b00000101 D
b10000101 E
b00010011 F
b00000000000000000000000000001100 H
#95
b00000000000101011000010110010011 ?
b00010101 D
b10010011 F
b000000000001 G
b00000000000000000000000000010000 H
b00000000000000000000000000000001 R
#96
b11111110011001011001100011100011 ?
b001 @
b1100011 A
b00000000000000000000000000000010 B
b11111110 C
b01100101 D
b10011000 E
b11100011 F
b111111111000 G
b00000000000000000000000000010100 H
0M
0O
0P
b11111111111111111111111111111000 R
#97
b11111110000000110001000011100011 ?
b00000011 D
b00010000 E
b111111110000 G
b00000000000000000000000000011000 H
b11111111111111111111111111110000 R
#98
b00001111111100000000001100010011 ?
b000 @
b0010011 A
b00000000000000000000000000000001 B
b00001111 C
b11110000 D
b00000011 E
b00010011 F
b000011111111 G
b00000000000000000000000000000000 H
0I
1M
1O
1P
b00000000000000000000000011111111 R
#99
b00000000000000000000010100010011 ?
b00000000 C
b00000000 D
b00000101 E
b000000000000 G
b00000000000000000000000000000100 H
b00000000000000000000000000000000 R
#100
b00000000000000000000010110010011 ?
b10010011 F
b00000000000000000000000000001000 H
#101
b00000000000001011000010100010011 ?
b00000101 D
b10000101 E
b00010011 F
b00000000000000000000000000001100 H
#102
b00000000000101011000010110010011 ?
b00010101 D
b10010011 F
b000000000001 G
b00000000000000000000000000010000 H
b00000000000000000000000000000001 R
#103
b11111110011001011001100011100011 ?
b001 @
b1100011 A
b00000000000000000000000000000010 B
b11111110 C
b01100101 D
b10011000 E
b11100011 F
b111111111000 G
b00000000000000000000000000010100 H
0M
0O
0P
1Q
b11111111111111111111111111111000 R
#104
b11111110000000110001000011100011 ?
b00000011 D
b00010000 E
b111111110000 G
b00000000000000000000000000011000 H
b11111111111111111111111111110000 R
#105
b00001111111100000000001100010011 ?
b000 @
b0010011 A
b00000000000000000000000000000001 B
b00001111 C
b11110000 D
b00000011 E
b00010011 F
b000011111111 G
b00000000000000000000000000000000 H
1I
1M
1O
1P
0Q
b00000000000000000000000011111111 R
#106
b00000000000000000000010100010011 ?
b00000000 C
b00000000 D
b00000101 E
b000000000000 G
b00000000000000000000000000000100 H
b00000000000000000000000000000000 R
#107
b00000000000000000000010110010011 ?
b10010011 F
b00000000000000000000000000001000 H
#108
b00000000000001011000010100010011 ?
b00000101 D
b10000101 E
b00010011 F
b00000000000000000000000000001100 H
#109
b00000000000101011000010110010011 ?
b00010101 D
b10010011 F
b000000000001 G
b00000000000000000000000000010000 H
b00000000000000000000000000000001 R
#110
b11111110011001011001100011100011 ?
b001 @
b1100011 A
b00000000000000000000000000000010 B
b11111110 C
b01100101 D
b10011000 E
b11100011 F
b111111111000 G
b00000000000000000000000000010100 H
0M
0O
0P
b11111111111111111111111111111000 R
#111
b11111110000000110001000011100011 ?
b00000011 D
b00010000 E
b111111110000 G
b00000000000000000000000000011000 H
b11111111111111111111111111110000 R
#112
b00001111111100000000001100010011 ?
b000 @
b0010011 A
b00000000000000000000000000000001 B
b00001111 C
b11110000 D
b00000011 E
b00010011 F
b000011111111 G
b00000000000000000000000000000000 H
0I
1M
1O
1P
b00000000000000000000000011111111 R
#113
b00000000000000000000010100010011 ?
b00000000 C
b00000000 D
b00000101 E
b000000000000 G
b00000000000000000000000000000100 H
b00000000000000000000000000000000 R
#114
b00000000000000000000010110010011 ?
b10010011 F
b00000000000000000000000000001000 H
#115
b00000000000001011000010100010011 ?
b00000101 D
b10000101 E
b00010011 F
b00000000000000000000000000001100 H
#116
b00000000000101011000010110010011 ?
b00010101 D
b10010011 F
b000000000001 G
b00000000000000000000000000010000 H
b00000000000000000000000000000001 R
#117
b11111110011001011001100011100011 ?
b001 @
b1100011 A
b00000000000000000000000000000010 B
b11111110 C
b01100101 D
b10011000 E
b11100011 F
b111111111000 G
b00000000000000000000000000010100 H
0M
0O
0P
1Q
b11111111111111111111111111111000 R
#118
b11111110000000110001000011100011 ?
b00000011 D
b00010000 E
b111111110000 G
b00000000000000000000000000011000 H
b11111111111111111111111111110000 R
#119
b00001111111100000000001100010011 ?
b000 @
b0010011 A
b00000000000000000000000000000001 B
b00001111 C
b11110000 D
b00000011 E
b00010011 F
b000011111111 G
b00000000000000000000000000000000 H
1I
1M
1O
1P
0Q
b00000000000000000000000011111111 R
#120
b00000000000000000000010100010011 ?
b00000000 C
b00000000 D
b00000101 E
b000000000000 G
b00000000000000000000000000000100 H
b00000000000000000000000000000000 R
#121
b00000000000000000000010110010011 ?
b10010011 F
b00000000000000000000000000001000 H
#122
b00000000000001011000010100010011 ?
b00000101 D
b10000101 E
b00010011 F
b00000000000000000000000000001100 H
#123
b00000000000101011000010110010011 ?
b00010101 D
b10010011 F
b000000000001 G
b00000000000000000000000000010000 H
b00000000000000000000000000000001 R
#124
b11111110011001011001100011100011 ?
b001 @
b1100011 A
b00000000000000000000000000000010 B
b11111110 C
b01100101 D
b10011000 E
b11100011 F
b111111111000 G
b00000000000000000000000000010100 H
0M
0O
0P
b11111111111111111111111111111000 R
#125
b11111110000000110001000011100011 ?
b00000011 D
b00010000 E
b111111110000 G
b00000000000000000000000000011000 H
b11111111111111111111111111110000 R
#126
b00001111111100000000001100010011 ?
b000 @
b0010011 A
b00000000000000000000000000000001 B
b00001111 C
b11110000 D
b00000011 E
b00010011 F
b000011111111 G
b00000000000000000000000000000000 H
0I
1M
1O
1P
b00000000000000000000000011111111 R
#127
b00000000000000000000010100010011 ?
b00000000 C
b00000000 D
b00000101 E
b000000000000 G
b00000000000000000000000000000100 H
b00000000000000000000000000000000 R
#128
b00000000000000000000010110010011 ?
b10010011 F
b00000000000000000000000000001000 H
#129
b00000000000001011000010100010011 ?
b00000101 D
b10000101 E
b00010011 F
b00000000000000000000000000001100 H
#130
b00000000000101011000010110010011 ?
b00010101 D
b10010011 F
b000000000001 G
b00000000000000000000000000010000 H
b00000000000000000000000000000001 R
#131
b11111110011001011001100011100011 ?
b001 @
b1100011 A
b00000000000000000000000000000010 B
b11111110 C
b01100101 D
b10011000 E
b11100011 F
b111111111000 G
b00000000000000000000000000010100 H
0M
0O
0P
1Q
b11111111111111111111111111111000 R
#132
b11111110000000110001000011100011 ?
b00000011 D
b00010000 E
b111111110000 G
b00000000000000000000000000011000 H
b11111111111111111111111111110000 R
#133
b00001111111100000000001100010011 ?
b000 @
b0010011 A
b00000000000000000000000000000001 B
b00001111 C
b11110000 D
b00000011 E
b00010011 F
b000011111111 G
b00000000000000000000000000000000 H
1I
1M
1O
1P
0Q
b00000000000000000000000011111111 R
#134
b00000000000000000000010100010011 ?
b00000000 C
b00000000 D
b00000101 E
b000000000000 G
b00000000000000000000000000000100 H
b00000000000000000000000000000000 R
#135
b00000000000000000000010110010011 ?
b10010011 F
b00000000000000000000000000001000 H
#136
b00000000000001011000010100010011 ?
b00000101 D
b10000101 E
b00010011 F
b00000000000000000000000000001100 H
#137
b00000000000101011000010110010011 ?
b00010101 D
b10010011 F
b000000000001 G
b00000000000000000000000000010000 H
b00000000000000000000000000000001 R
